{"room_number": "527D", "qr": "2C2870", "measured_temp": "21.6", "issue_heating": "", "issue_motion": "", "issue_temperature_sensor": "", "issue_door": "", "issue_window": "", "issue_heating_switch": "", "issue_kitchen_switch": "", "issue_wifi": "", "problem_description": "", "solution": "", "short_uuid": "2C2-870\n", "mac_address": "02:42:AC:12:00:02", "timestamp": "25-09-2023_18-34-09", "last_motion_time": "25-09-2023 18:34:07", "last_motion_state": 0, "voltage_state": "DETECT", "temp": "23.9375", "broker_connection": "NOT CONNECTED"}