{"room_number": "524", "qr": "29E-BCD", "measured_temp": "21.6", "issue_heating": "", "issue_motion": "", "issue_temperature_sensor": "", "issue_door": "", "issue_window": "Kontaktron w oknie nie dzia\u0142a. Okno widnieje jako otwarte zawsze.", "issue_heating_switch": "", "issue_kitchen_switch": "", "issue_wifi": "", "problem_description": "", "solution": "Wymienione rpi+poe", "short_uuid": "2DC-2A5\n", "mac_address": "02:42:AC:12:00:03", "timestamp": "29-09-2023_21-34-28", "last_motion_time": "29-09-2023 21:33:51", "last_motion_state": 0, "voltage_state": "DETECT", "temp": "25.0", "broker_connection": "NOT CONNECTED"}